MANIFEST.in
README.md
setup.py
insist/__init__.py
insist/insist.py
insist/util.py
insist.egg-info/PKG-INFO
insist.egg-info/SOURCES.txt
insist.egg-info/dependency_links.txt
insist.egg-info/top_level.txt