Metadata-Version: 1.1
Name: insist
Version: 0.1
Summary: An easy-to-use assertion library for Python
Home-page: https://github.com/ray-harris-net/insist
Author: Ray Harris
Author-email: ray@harris.net
License: LICENSE
Platform: UNKNOWN
Classifier: Development Status :: 3 - Alpha
Classifier: Programming Language :: Python :: 2
Classifier: Programming Language :: Python :: 2.6
Classifier: Programming Language :: Python :: 2.7
Classifier: Programming Language :: Python :: 3
